AUTHORS
CHANGELOG.txt
DESCRIPTION
LICENSE
MANIFEST.in
README.rst
setup.py
django_people.egg-info/PKG-INFO
django_people.egg-info/SOURCES.txt
django_people.egg-info/dependency_links.txt
django_people.egg-info/requires.txt
django_people.egg-info/top_level.txt
people/__init__.py
people/admin.py
people/cms_plugins.py
people/models.py
people/settings.py
people/locale/zh/LC_MESSAGES/django.mo
people/locale/zh/LC_MESSAGES/django.po
people/migrations/0001_initial.py
people/migrations/__init__.py
people/south_migrations/0001_initial.py
people/south_migrations/0002_auto__add_field_linktype_slug.py
people/south_migrations/0003_auto__add_personpluginmodel.py
people/south_migrations/0004_auto__add_field_persontranslation_short_bio.py
people/south_migrations/0005_auto__add_field_persontranslation_roman_first_name__add_field_persontr.py
people/south_migrations/0006_copy_names_into_roman_or_non_roman_fields.py
people/south_migrations/0007_auto__del_field_persontranslation_last_name__del_field_persontranslati.py
people/south_migrations/0008_auto__add_field_person_roman_first_name__add_field_person_roman_last_n.py
people/south_migrations/0009_move_name_fields_to_person_model.py
people/south_migrations/0010_auto__del_field_persontranslation_non_roman_last_name__del_field_perso.py
people/south_migrations/0011_auto__add_nationality__add_nationalitytranslation__add_field_person_na.py
people/south_migrations/0012_rename_tables_temporarily.py
people/south_migrations/0013_auto__add_roletranslation__add_unique_roletranslation_language_code_ma.py
people/south_migrations/0014_move_from_simpletranslation_to_hvad.py
people/south_migrations/0015_auto__del_roletranslationrenamed__del_persontranslationrenamed__del_li.py
people/south_migrations/0016_rename_plugin_table.py
people/south_migrations/__init__.py
people/templates/people/person_plugin.html
people/tests/__init__.py
people/tests/models_tests.py
people/tests/settings.py
people/tests/test_settings.py
people/tests/urls.py
people/tests/test_app/__init__.py
people/tests/test_app/models.py
people/tests/test_app/templates/base.html
people/tests/test_app/templates/standard.html