Metadata-Version: 1.0
Name: django-people
Version: 1.1
Summary: An app for showing person profiles, for example for your "About us" section.
